tree_sitter_xml-0.7.0.dist-info/RECORD
tree_sitter_xml-0.7.0.dist-info/LICENSE
tree_sitter_xml-0.7.0.dist-info/WHEEL
tree_sitter_xml-0.7.0.dist-info/top_level.txt
tree_sitter_xml-0.7.0.dist-info/METADATA
tree_sitter_xml/__init__.pyi
tree_sitter_xml/binding.c
tree_sitter_xml/__init__.py
tree_sitter_xml/py.typed
tree_sitter_xml/_binding.abi3.so
tree_sitter_xml/queries/xml/highlights.scm
tree_sitter_xml/queries/dtd/highlights.scm
