Metadata-Version: 2.1
Name: tree-sitter-xml
Version: 0.7.0
Summary: XML & DTD grammars for tree-sitter
Author-email: ObserverOfTime <chronobserver@disroot.org>, Amaan Qureshi <amaanq12@gmail.com>
License: MIT
Project-URL: Homepage, https://github.com/tree-sitter/tree-sitter-xml
Project-URL: Sponsor, https://github.com/sponsors/ObserverOfTime
Keywords: incremental,parsing,tree-sitter,xml
Classifier: Intended Audience :: Developers
Classifier: License :: OSI Approved :: MIT License
Classifier: Topic :: Software Development :: Compilers
Classifier: Topic :: Text Processing :: Linguistic
Classifier: Typing :: Typed
Requires-Python: >=3.9
License-File: LICENSE
Provides-Extra: core
Requires-Dist: tree-sitter~=0.22; extra == "core"
